{
  "users": [
    {
      "name": "Maxmillanq2",
      "mobile": "8888888888",
      "email": "max@gmail.com",
      "pasword": "123qwe",
      "id": 6
    },
    {
      "name": "Andrew Smith",
      "mobile": "99999999",
      "email": "andrew@gmail.com",
      "pasword": "123qwe",
      "id": 7
    },
    {
      "name": "Harish Sadu",
      "mobile": "99999999",
      "email": "harish@gmail.com",
      "pasword": "bot2605",
      "id": 8
    },
    {
      "name": "Harendar Sen",
      "mobile": "88888888",
      "email": "harendar@gmail.com",
      "pasword": "bot2605",
      "id": 9
    },
    {
      "name": "ROCKY",
      "mobile": "9832944718",
      "email": "admin@onetouch.com",
      "pasword": "bot2605",
      "id": 10
    },
    {
      "name": "Max Joh",
      "mobile": "22222222",
      "email": "test@test.com",
      "pasword": "bot2605",
      "id": 11
    },
    {
      "name": "test",
      "mobile": "9876543210",
      "email": "test@gmail.com",
      "pasword": "1234qwe",
      "id": 13
    },
    {
      "name": "test",
      "mobile": "9832944718",
      "email": "admin@onetouch.com",
      "pasword": "bot2605",
      "id": 14
    },
    {
      "name": "Niraj Saxena",
      "mobile": "9876543210",
      "email": "niraj@gmail.com",
      "pasword": "bot2605",
      "id": 15
    },
    {
      "name": "pwd",
      "mobile": "9832944718",
      "email": "admin@onetouch.com",
      "pasword": "bot2605",
      "id": 16
    },
    {
      "name": "Mahesh Kumar",
      "mobile": "777777777711",
      "email": "mahesh@gmail.com",
      "pasword": "123",
      "id": 17
    }
  ]
}